onesecondtrader/__init__.py
onesecondtrader/brokers/__init__.py
onesecondtrader/brokers/base.py
onesecondtrader/brokers/simulated.py
onesecondtrader/events/__init__.py
onesecondtrader/events/base.py
onesecondtrader/events/market/__init__.py
onesecondtrader/events/market/bar_processed.py
onesecondtrader/events/market/bar_received.py
onesecondtrader/events/orders/__init__.py
onesecondtrader/events/orders/base.py
onesecondtrader/events/orders/expirations.py
onesecondtrader/events/orders/fills.py
onesecondtrader/events/requests/__init__.py
onesecondtrader/events/requests/base.py
onesecondtrader/events/requests/order_cancellation.py
onesecondtrader/events/requests/order_modification.py
onesecondtrader/events/requests/order_submission.py
onesecondtrader/events/responses/__init__.py
onesecondtrader/events/responses/base.py
onesecondtrader/events/responses/cancellations.py
onesecondtrader/events/responses/modifications.py
onesecondtrader/events/responses/orders.py
onesecondtrader/indicators/__init__.py
onesecondtrader/indicators/base.py
onesecondtrader/indicators/market_fields.py
onesecondtrader/indicators/moving_averages.py
onesecondtrader/messaging/__init__.py
onesecondtrader/messaging/eventbus.py
onesecondtrader/messaging/subscriber.py
onesecondtrader/models/__init__.py
onesecondtrader/models/bar_fields.py
onesecondtrader/models/bar_period.py
onesecondtrader/models/order_types.py
onesecondtrader/models/rejection_reasons.py
onesecondtrader/models/trade_sides.py
onesecondtrader/secmaster/__init__.py
onesecondtrader/secmaster/schema_versions/__init__.py
onesecondtrader/secmaster/schema_versions/secmaster_schema_v1.sql
onesecondtrader/secmaster/utils.py
onesecondtrader-0.52.0.dist-info/METADATA
onesecondtrader-0.52.0.dist-info/WHEEL
onesecondtrader-0.52.0.dist-info/licenses/LICENSE
onesecondtrader-0.52.0.dist-info/RECORD
