Metadata-Version: 2.4
Name: onesecondtrader
Version: 0.52.0
Summary: The Trading Infrastructure Toolkit for Python. Research, simulate, and deploy algorithmic trading strategies — all in one place.
License-File: LICENSE
Author: Nils P. Kujath
Author-email: 63961429+NilsKujath@users.noreply.github.com
Requires-Python: >=3.11
Classifier: Programming Language :: Python :: 3
Classifier: Programming Language :: Python :: 3.11
Classifier: Programming Language :: Python :: 3.12
Classifier: Programming Language :: Python :: 3.13
Classifier: Programming Language :: Python :: 3.14
Requires-Dist: databento (>=0.69.0,<0.70.0)
Requires-Dist: fastapi (>=0.128.0,<0.129.0)
Requires-Dist: ib-async (>=2.1.0,<3.0.0)
Requires-Dist: matplotlib (>=3.10.7,<4.0.0)
Requires-Dist: mplfinance (>=0.12.10b0,<0.13.0)
Requires-Dist: pandas (>=2.3.1,<3.0.0)
Requires-Dist: python-dotenv (>=1.0.0,<2.0.0)
Requires-Dist: tqdm (>=4.67.1,<5.0.0)
Requires-Dist: uvicorn (>=0.40.0,<0.41.0)
